PxxFontDecrypt/__init__.py
PxxFontDecrypt/decrypt.py
pxx_font_decrypt-1.0.0.dist-info/LICENSE
pxx_font_decrypt-1.0.0.dist-info/METADATA
pxx_font_decrypt-1.0.0.dist-info/WHEEL
pxx_font_decrypt-1.0.0.dist-info/RECORD
